django_discord/__init__.py
Django_Discord-0.0.1.dist-info/METADATA
Django_Discord-0.0.1.dist-info/WHEEL
Django_Discord-0.0.1.dist-info/top_level.txt
Django_Discord-0.0.1.dist-info/RECORD
